notti/__init__.py
notti-1.0.dist-info/DESCRIPTION.rst
notti-1.0.dist-info/METADATA
notti-1.0.dist-info/RECORD
notti-1.0.dist-info/WHEEL
notti-1.0.dist-info/metadata.json
notti-1.0.dist-info/top_level.txt
